AUTHORS
CHANGELOG.txt
DESCRIPTION
LICENSE
MANIFEST.in
README.rst
setup.cfg
setup.py
aps_purchasing/__init__.py
aps_purchasing/admin.py
aps_purchasing/forms.py
aps_purchasing/models.py
aps_purchasing/urls.py
aps_purchasing/views.py
aps_purchasing/fixtures/bootstrap_auth.json
aps_purchasing/migrations/0001_initial.py
aps_purchasing/migrations/0002_auto__add_field_quotationitem_manufacturer.py
aps_purchasing/migrations/__init__.py
aps_purchasing/static/aps_purchasing/css/jquery.dataTables.css
aps_purchasing/static/aps_purchasing/images/Sorting icons.psd
aps_purchasing/static/aps_purchasing/images/back_disabled.png
aps_purchasing/static/aps_purchasing/images/back_enabled.png
aps_purchasing/static/aps_purchasing/images/back_enabled_hover.png
aps_purchasing/static/aps_purchasing/images/favicon.ico
aps_purchasing/static/aps_purchasing/images/forward_disabled.png
aps_purchasing/static/aps_purchasing/images/forward_enabled.png
aps_purchasing/static/aps_purchasing/images/forward_enabled_hover.png
aps_purchasing/static/aps_purchasing/images/sort_asc.png
aps_purchasing/static/aps_purchasing/images/sort_asc_disabled.png
aps_purchasing/static/aps_purchasing/images/sort_both.png
aps_purchasing/static/aps_purchasing/images/sort_desc.png
aps_purchasing/static/aps_purchasing/images/sort_desc_disabled.png
aps_purchasing/static/aps_purchasing/js/jquery.dataTables.min.js
aps_purchasing/static/aps_purchasing/js/libs/jquery-1.9.1.js
aps_purchasing/templates/aps_purchasing/quotation_upload.html
aps_purchasing/templates/aps_purchasing/report.html
aps_purchasing/templates/aps_purchasing/upload_base.html
aps_purchasing/tests/.coveragerc
aps_purchasing/tests/__init__.py
aps_purchasing/tests/factories.py
aps_purchasing/tests/forms_tests.py
aps_purchasing/tests/models_tests.py
aps_purchasing/tests/runtests.py
aps_purchasing/tests/south_settings.py
aps_purchasing/tests/test_settings.py
aps_purchasing/tests/urls.py
aps_purchasing/tests/files/Quotation.csv
django_aps_purchasing.egg-info/PKG-INFO
django_aps_purchasing.egg-info/SOURCES.txt
django_aps_purchasing.egg-info/dependency_links.txt
django_aps_purchasing.egg-info/requires.txt
django_aps_purchasing.egg-info/top_level.txt