Metadata-Version: 1.0
Name: django-aps-purchasing
Version: 0.3
Summary: The purchasing module for django-apsara.
